CHANGES.rst
CONTRIBUTORS.rst
MANIFEST.in
README.rst
setup.cfg
setup.py
docs/LICENSE.GPL
docs/LICENSE.rst
docs/index.rst
docs/screen-all-detail.jpg
docs/screen-all-overview.jpg
docs/screen-folder1.jpg
docs/screen-move_portlet.jpg
src/collective/__init__.py
src/collective.fgrcon.portletadmin.egg-info/PKG-INFO
src/collective.fgrcon.portletadmin.egg-info/SOURCES.txt
src/collective.fgrcon.portletadmin.egg-info/dependency_links.txt
src/collective.fgrcon.portletadmin.egg-info/entry_points.txt
src/collective.fgrcon.portletadmin.egg-info/namespace_packages.txt
src/collective.fgrcon.portletadmin.egg-info/not-zip-safe
src/collective.fgrcon.portletadmin.egg-info/requires.txt
src/collective.fgrcon.portletadmin.egg-info/top_level.txt
src/collective/fgrcon/__init__.py
src/collective/fgrcon/portletadmin/__init__.py
src/collective/fgrcon/portletadmin/configure.zcml
src/collective/fgrcon/portletadmin/interfaces.py
src/collective/fgrcon/portletadmin/setuphandlers.py
src/collective/fgrcon/portletadmin/testing.py
src/collective/fgrcon/portletadmin/browser/__init__.py
src/collective/fgrcon/portletadmin/browser/configure.zcml
src/collective/fgrcon/portletadmin/browser/delete_portlet.py
src/collective/fgrcon/portletadmin/browser/move_portlet.py
src/collective/fgrcon/portletadmin/browser/portletadmin.py
src/collective/fgrcon/portletadmin/browser/overrides/.gitkeep
src/collective/fgrcon/portletadmin/browser/static/.gitkeep
src/collective/fgrcon/portletadmin/browser/templates/portletadmin.pt
src/collective/fgrcon/portletadmin/locales/collective.fgrcon.portletadmin.pot
src/collective/fgrcon/portletadmin/locales/update.sh
src/collective/fgrcon/portletadmin/profiles/default/browserlayer.xml
src/collective/fgrcon/portletadmin/profiles/default/metadata.xml
src/collective/fgrcon/portletadmin/profiles/default/registry.xml
src/collective/fgrcon/portletadmin/profiles/uninstall/browserlayer.xml
src/collective/fgrcon/portletadmin/static/.gitkeep
src/collective/fgrcon/portletadmin/static/info.png
src/collective/fgrcon/portletadmin/static/portletadmin.css
src/collective/fgrcon/portletadmin/static/screenshot.jpg
src/collective/fgrcon/portletadmin/static/selmanager.js
src/collective/fgrcon/portletadmin/tests/__init__.py
src/collective/fgrcon/portletadmin/tests/test_robot.py
src/collective/fgrcon/portletadmin/tests/test_setup.py
src/collective/fgrcon/portletadmin/tests/robot/test_example.robot