Metadata-Version: 1.1
Name: collective.fgrcon.portletadmin
Version: 1.2
Summary: A Plone utility for inspecting and manipulating context  portlet assignments
Home-page: https://pypi.python.org/pypi/collective.fgrcon.portletadmin
Author: Franz Gerhard Reinisch
Author-email: franz@fgrcon.net
License: GPL version 2
Keywords: Python Plone
Platform: UNKNOWN
Classifier: Environment :: Web Environment
Classifier: Framework :: Plone
Classifier: Framework :: Plone :: 5.1
Classifier: Programming Language :: Python
Classifier: Programming Language :: Python :: 2.7
Classifier: Operating System :: OS Independent
Classifier: License :: OSI Approved :: GNU General Public License v2 (GPLv2)
